epigraphhub/__init__.py
epigraphhub/__main__.py
epigraphhub/analysis/__init__.py
epigraphhub/analysis/clustering.py
epigraphhub/analysis/epistats.py
epigraphhub/analysis/forecast_models/lstm_models.py
epigraphhub/analysis/forecast_models/metrics.py
epigraphhub/analysis/forecast_models/ngboost_models.py
epigraphhub/analysis/forecast_models/plots.py
epigraphhub/analysis/forecast_models/sklearn_models.py
epigraphhub/analysis/preprocessing.py
epigraphhub/analysis/rtestim.py
epigraphhub/connection.py
epigraphhub/data/.env
epigraphhub/data/__init__.py
epigraphhub/data/_config.py
epigraphhub/data/brasil/__init__.py
epigraphhub/data/brasil/sinan/__init__.py
epigraphhub/data/brasil/sinan/extract.py
epigraphhub/data/brasil/sinan/loading.py
epigraphhub/data/brasil/sinan/viz.py
epigraphhub/data/colombia/__init__.py
epigraphhub/data/colombia/extract.py
epigraphhub/data/colombia/loading.py
epigraphhub/data/epigraphhub_db.py
epigraphhub/data/foph/__init__.py
epigraphhub/data/foph/extract.py
epigraphhub/data/foph/loading.py
epigraphhub/data/foph/schema.json
epigraphhub/data/foph/transform.py
epigraphhub/data/foph/viz.py
epigraphhub/data/geoupload.py
epigraphhub/data/ggtrends.py
epigraphhub/data/owid/__init__.py
epigraphhub/data/owid/extract.py
epigraphhub/data/owid/loading.py
epigraphhub/data/owid/transform.py
epigraphhub/data/sinan_fetch.py
epigraphhub/data/worldbank.py
epigraphhub/data/worldpop.py
epigraphhub/settings.py
epigraphhub/utils/__init__.py
epigraphhub/utils/_config.py
epigraphhub-2.1.1.dist-info/LICENSE
epigraphhub-2.1.1.dist-info/METADATA
epigraphhub-2.1.1.dist-info/WHEEL
epigraphhub-2.1.1.dist-info/entry_points.txt
epigraphhub-2.1.1.dist-info/RECORD
