Metadata-Version: 2.1
Name: epigraphhub
Version: 2.1.1
Summary: Epigraphhub Python package
Home-page: https://github.com/thegraphnetwork/epigraphhub_py
License: GNU GPL v3.0
Keywords: epidemiology
Author: thegraphnetwork
Author-email: fccoelho@gmail.com
Requires-Python: >=3.9,<3.11
Classifier: Development Status :: 3 - Alpha
Classifier: Intended Audience :: Developers
Classifier: License :: OSI Approved :: GNU General Public License v3 or later (GPLv3+)
Classifier: License :: Other/Proprietary License
Classifier: Operating System :: OS Independent
Classifier: Programming Language :: Python :: 3
Classifier: Programming Language :: Python :: 3.9
Classifier: Programming Language :: Python :: 3.10
Classifier: Topic :: Software Development :: Libraries :: Python Modules
Provides-Extra: ml
Provides-Extra: viz
Requires-Dist: GeoAlchemy2 (>=0.10.0)
Requires-Dist: PyYAML (>=5.0)
Requires-Dist: SQLAlchemy (>=1.4.29,<2.0.0)
Requires-Dist: arviz (>=0.12.0) ; extra == "viz"
Requires-Dist: click (>=8.1.0)
Requires-Dist: geopandas (>=0.10.2)
Requires-Dist: ibis-framework (>=3.2.0,<4)
Requires-Dist: joblib (>=1.1.0)
Requires-Dist: jupyter (>=1.0.0)
Requires-Dist: loguru (>=0.6.0)
Requires-Dist: matplotlib (>=3.5.1) ; extra == "viz"
Requires-Dist: ngboost (>=0.3.13,<0.4) ; extra == "ml"
Requires-Dist: numpy (>=1.20.3,<2)
Requires-Dist: pandas (>=1.2,<2)
Requires-Dist: pangres (>=4.1.2)
Requires-Dist: plotly (>=5) ; extra == "viz"
Requires-Dist: psycopg2-binary (>=2.9.3)
Requires-Dist: pymc (>=4.2.0)
Requires-Dist: pytrends (>=4.7.3) ; extra == "ml"
Requires-Dist: rich (>=12.4.4,<13)
Requires-Dist: rioxarray (>=0.10.2)
Requires-Dist: scikit-learn (>=1.0.2,<1.3) ; extra == "ml"
Requires-Dist: scipy (>=1.8.0,<1.13)
Requires-Dist: sodapy (>=2.2.0)
Requires-Dist: sshtunnel (>=0.4.0)
Requires-Dist: tabulate (>=0.8.9)
Requires-Dist: tensorflow (>=2.5.0) ; extra == "ml"
Requires-Dist: typer[all] (>=0.4.0)
Requires-Dist: wbgapi (>=1.0.7)
Requires-Dist: wget (>=3.2)
Project-URL: Repository, https://github.com/thegraphnetwork/epigraphhub_py
